__init__.py
semantic_load/calculator.py
sl_gme-0.1.0.dist-info/licenses/LICENSE
sl_gme-0.1.0.dist-info/METADATA
sl_gme-0.1.0.dist-info/WHEEL
sl_gme-0.1.0.dist-info/top_level.txt
sl_gme-0.1.0.dist-info/RECORD
