Metadata-Version: 2.4
Name: sl-gme
Version: 0.1.0
Summary: Semantic-Load-Guided Model Evolution
Author-email: Roberto Jimenez <roberto@example.com>, DeepSeek Assistant <assistant@deepseek.com>
License: Apache 2.0
Project-URL: Homepage, https://github.com/roberto-jimenez/sl-gme
Project-URL: Documentation, https://roberto-jimenez.github.io/sl-gme
Project-URL: Repository, https://github.com/roberto-jimenez/sl-gme.git
Classifier: Development Status :: 3 - Alpha
Classifier: Intended Audience :: Science/Research
Classifier: License :: OSI Approved :: Apache Software License
Classifier: Programming Language :: Python :: 3.9
Classifier: Programming Language :: Python :: 3.10
Classifier: Programming Language :: Python :: 3.11
Classifier: Topic :: Scientific/Engineering :: Artificial Intelligence
Requires-Python: >=3.9
License-File: LICENSE
Requires-Dist: torch>=2.0.0
Requires-Dist: transformers>=4.30.0
Requires-Dist: numpy>=1.24.0
Requires-Dist: scipy>=1.10.0
Requires-Dist: datasets>=2.12.0
Requires-Dist: pydantic>=2.0.0
Requires-Dist: tqdm>=4.65.0
Provides-Extra: dev
Requires-Dist: pytest>=7.3.0; extra == "dev"
Requires-Dist: black>=23.3.0; extra == "dev"
Requires-Dist: flake8>=6.0.0; extra == "dev"
Requires-Dist: mypy>=1.3.0; extra == "dev"
Requires-Dist: pre-commit>=3.3.0; extra == "dev"
Provides-Extra: viz
Requires-Dist: matplotlib>=3.7.0; extra == "viz"
Requires-Dist: seaborn>=0.12.0; extra == "viz"
Provides-Extra: notebook
Requires-Dist: jupyter>=1.0.0; extra == "notebook"
Requires-Dist: ipywidgets>=8.0.0; extra == "notebook"
Dynamic: license-file
